pomo_tui-0.1.1.dist-info/licenses/LICENSE
pomodoro_cli/__init__.py
pomodoro_cli/__main__.py
pomodoro_cli/app.py
pomo_tui-0.1.1.dist-info/METADATA
pomo_tui-0.1.1.dist-info/WHEEL
pomo_tui-0.1.1.dist-info/entry_points.txt
pomo_tui-0.1.1.dist-info/top_level.txt
pomo_tui-0.1.1.dist-info/RECORD
