Metadata-Version: 2.4
Name: pomo-tui
Version: 0.1.1
Summary: Terminal-based Pomodoro timer with TUI and sound notifications
Author: newbie1223
License: MIT License
Requires-Python: >=3.9
License-File: LICENSE
Dynamic: license-file
